linguify/__init__.py
linguify/linguify.py
linguify/main.py
Linguify-2.8.3.dist-info/LICENSE
Linguify-2.8.3.dist-info/METADATA
Linguify-2.8.3.dist-info/WHEEL
Linguify-2.8.3.dist-info/entry_points.txt
Linguify-2.8.3.dist-info/top_level.txt
Linguify-2.8.3.dist-info/RECORD
